{
  "args": {
    "analysis_frame_range": null,
    "analysis_frame_step": 1,
    "analysis_frames": null,
    "beam_direction": null,
    "composition": "62 C, 24 H, 40 O, 8 V",
    "detector_frames": null,
    "detector_xy_swapped": false,
    "dmax": 20.0,
    "dmin": 0.4,
    "dynamical_cluster_sigma_alpha": 1.0,
    "dynamical_coupling_q0": 0.25,
    "dynamical_environment_tolerance": 0.01,
    "dynamical_neighbor_radius": 0.12,
    "dynamical_neighbor_sigma": null,
    "dynamical_row_direction_limit": 2,
    "dynamical_row_max_steps": 5,
    "dynamical_row_sigma": 0.25,
    "dynamical_weight_row": 1.0,
    "dynamical_weight_self": 1.0,
    "dynamical_weight_zone": 1.0,
    "dynamical_zone_axis_sigma": 2.0,
    "dynamical_zone_sigma": 0.06,
    "excitation_tolerance": 0.01,
    "filter_untrusted": false,
    "gxparm": null,
    "integrate": null,
    "mode": "proxy",
    "orientation_gxparm": null,
    "orientation_only": true,
    "orientation_score_formulation": "log_n_eff",
    "orientation_sigma_alpha": 0.5,
    "orientation_sigma_axis_deg": null,
    "orientation_sigma_deg": 0.2,
    "output_dir": "bloch_wave_analyser_project/mfm300_stream_dyn",
    "pets_align_gxparm": null,
    "pets_angle_reference": "absolute",
    "pets_detector_flip_x": false,
    "pets_detector_flip_y": false,
    "pets_detector_nx": 0,
    "pets_detector_ny": 0,
    "pets_detector_omega_map_mode": "frame_absolute",
    "pets_detector_omega_offset_deg": 0.0,
    "pets_detector_omega_sign": 1.0,
    "pets_detector_projection": "full",
    "pets_detector_swap_xy": false,
    "pets_hkl": null,
    "pets_include_domega_in_lattice": false,
    "pets_invert_rotation": false,
    "pets_orientation_mode": "pets_ab_xy",
    "pets_project": null,
    "pets_pts2": null,
    "pets_ptsopt": null,
    "pets_rprofall": null,
    "pets_ub_convention": "columns",
    "pets_use_only_for_calc": false,
    "show_untrusted_rectangles": false,
    "stream": "/home/bubl3932/files/MFM300_VIII/MFM300_UK_2ndGrid_spot_4_220mm_0deg_150nm_50ms_20250524/runs_20251201_110132/early_break.stream",
    "stream_det_shift_sign": 1.0,
    "stream_mirror_x_axis": true,
    "thickness": null,
    "thickness_start": null,
    "thickness_step": null,
    "thickness_stop": null,
    "xdsinp": null
  },
  "argv": [
    "bloch_wave_analyser_project/examples/run_analysis.py",
    "--stream",
    "/home/bubl3932/files/MFM300_VIII/MFM300_UK_2ndGrid_spot_4_220mm_0deg_150nm_50ms_20250524/runs_20251201_110132/early_break.stream",
    "--composition",
    "62 C, 24 H, 40 O, 8 V",
    "--dmin",
    "0.4",
    "--dmax",
    "20.0",
    "--excitation-tolerance",
    "0.01",
    "--mode",
    "proxy",
    "--orientation-only",
    "--dynamical-environment-tolerance",
    "0.01",
    "--dynamical-neighbor-radius",
    "0.12",
    "--dynamical-zone-axis-sigma",
    "2.0",
    "--dynamical-zone-sigma",
    "0.06",
    "--dynamical-row-direction-limit",
    "2",
    "--dynamical-row-max-steps",
    "5",
    "--dynamical-row-sigma",
    "0.25",
    "--dynamical-cluster-sigma-alpha",
    "1.0",
    "--output-dir",
    "bloch_wave_analyser_project/mfm300_stream_dyn"
  ]
}